{"ST_CAT_CODE":"CBTZD","ST_CAT_NAME":"成本调整单","ST_DOC_CLASS":"CBTZD","ST_APPROVAL_TYPE":null,"PROCESS_ID":null,"PC_W_FORM_ID":null,"PC_A_FORM_ID":null,"PC_P_FORM_ID":null,"M_W_FORM_ID":null,"M_A_FORM_ID":null,"ATT_CAT_CODE":null,"DESCRIPTION":null,"STATUS":null,"CREATION_DATE":null,"CREATED_BY":null,"LAST_UPDATE_DATE":null,"LAST_UPDATED_BY":null}
{"ST_CAT_CODE":"CGRK","ST_CAT_NAME":"采购入库单","ST_DOC_CLASS":"RKD","ST_APPROVAL_TYPE":null,"PROCESS_ID":null,"PC_W_FORM_ID":null,"PC_A_FORM_ID":null,"PC_P_FORM_ID":null,"M_W_FORM_ID":null,"M_A_FORM_ID":null,"ATT_CAT_CODE":null,"DESCRIPTION":null,"STATUS":null,"CREATION_DATE":null,"CREATED_BY":null,"LAST_UPDATE_DATE":null,"LAST_UPDATED_BY":null}
{"ST_CAT_CODE":"CGTH","ST_CAT_NAME":"采购退货单","ST_DOC_CLASS":"RKD","ST_APPROVAL_TYPE":null,"PROCESS_ID":null,"PC_W_FORM_ID":null,"PC_A_FORM_ID":null,"PC_P_FORM_ID":null,"M_W_FORM_ID":null,"M_A_FORM_ID":null,"ATT_CAT_CODE":null,"DESCRIPTION":null,"STATUS":null,"CREATION_DATE":null,"CREATED_BY":null,"LAST_UPDATE_DATE":null,"LAST_UPDATED_BY":null}
{"ST_CAT_CODE":"DBD","ST_CAT_NAME":"调拨单","ST_DOC_CLASS":"DBD","ST_APPROVAL_TYPE":null,"PROCESS_ID":null,"PC_W_FORM_ID":null,"PC_A_FORM_ID":null,"PC_P_FORM_ID":null,"M_W_FORM_ID":null,"M_A_FORM_ID":null,"ATT_CAT_CODE":null,"DESCRIPTION":null,"STATUS":null,"CREATION_DATE":null,"CREATED_BY":null,"LAST_UPDATE_DATE":null,"LAST_UPDATED_BY":null}
{"ST_CAT_CODE":"HWTZD","ST_CAT_NAME":"货位调整单","ST_DOC_CLASS":"HWTZD","ST_APPROVAL_TYPE":null,"PROCESS_ID":null,"PC_W_FORM_ID":null,"PC_A_FORM_ID":null,"PC_P_FORM_ID":null,"M_W_FORM_ID":null,"M_A_FORM_ID":null,"ATT_CAT_CODE":null,"DESCRIPTION":null,"STATUS":null,"CREATION_DATE":null,"CREATED_BY":null,"LAST_UPDATE_DATE":null,"LAST_UPDATED_BY":null}
{"ST_CAT_CODE":"LYCK","ST_CAT_NAME":"领用出库单","ST_DOC_CLASS":"CKD","ST_APPROVAL_TYPE":null,"PROCESS_ID":null,"PC_W_FORM_ID":null,"PC_A_FORM_ID":null,"PC_P_FORM_ID":null,"M_W_FORM_ID":null,"M_A_FORM_ID":null,"ATT_CAT_CODE":null,"DESCRIPTION":null,"STATUS":null,"CREATION_DATE":null,"CREATED_BY":null,"LAST_UPDATE_DATE":null,"LAST_UPDATED_BY":null}
{"ST_CAT_CODE":"LYSQD","ST_CAT_NAME":"领用申请单","ST_DOC_CLASS":"LLSQD","ST_APPROVAL_TYPE":null,"PROCESS_ID":"1d59bef0-2949-49c4-966e-fb488f7c1d0c","PC_W_FORM_ID":null,"PC_A_FORM_ID":"XC-ST_USE_APPLY","PC_P_FORM_ID":null,"M_W_FORM_ID":null,"M_A_FORM_ID":null,"ATT_CAT_CODE":"XC_ST_CAT","DESCRIPTION":null,"STATUS":null,"CREATION_DATE":null,"CREATED_BY":null,"LAST_UPDATE_DATE":"2016-12-27 10:37:10.0","LAST_UPDATED_BY":"de1c3523-85a7-49e5-806a-1ea7dca85b25"}
{"ST_CAT_CODE":"LYTK","ST_CAT_NAME":"领用退库单","ST_DOC_CLASS":"CKD","ST_APPROVAL_TYPE":null,"PROCESS_ID":null,"PC_W_FORM_ID":null,"PC_A_FORM_ID":null,"PC_P_FORM_ID":null,"M_W_FORM_ID":null,"M_A_FORM_ID":null,"ATT_CAT_CODE":null,"DESCRIPTION":null,"STATUS":null,"CREATION_DATE":null,"CREATED_BY":null,"LAST_UPDATE_DATE":null,"LAST_UPDATED_BY":null}
{"ST_CAT_CODE":"QTCK","ST_CAT_NAME":"其他出库单","ST_DOC_CLASS":"CKD","ST_APPROVAL_TYPE":null,"PROCESS_ID":null,"PC_W_FORM_ID":null,"PC_A_FORM_ID":null,"PC_P_FORM_ID":null,"M_W_FORM_ID":null,"M_A_FORM_ID":null,"ATT_CAT_CODE":null,"DESCRIPTION":null,"STATUS":null,"CREATION_DATE":null,"CREATED_BY":null,"LAST_UPDATE_DATE":null,"LAST_UPDATED_BY":null}
{"ST_CAT_CODE":"QTCK-H","ST_CAT_NAME":"其他出库单-红字","ST_DOC_CLASS":"CKD","ST_APPROVAL_TYPE":null,"PROCESS_ID":null,"PC_W_FORM_ID":null,"PC_A_FORM_ID":null,"PC_P_FORM_ID":null,"M_W_FORM_ID":null,"M_A_FORM_ID":null,"ATT_CAT_CODE":null,"DESCRIPTION":null,"STATUS":null,"CREATION_DATE":null,"CREATED_BY":null,"LAST_UPDATE_DATE":null,"LAST_UPDATED_BY":null}
{"ST_CAT_CODE":"QTRK","ST_CAT_NAME":"其他入库单","ST_DOC_CLASS":"RKD","ST_APPROVAL_TYPE":null,"PROCESS_ID":null,"PC_W_FORM_ID":null,"PC_A_FORM_ID":null,"PC_P_FORM_ID":null,"M_W_FORM_ID":null,"M_A_FORM_ID":null,"ATT_CAT_CODE":null,"DESCRIPTION":null,"STATUS":null,"CREATION_DATE":null,"CREATED_BY":null,"LAST_UPDATE_DATE":null,"LAST_UPDATED_BY":null}
{"ST_CAT_CODE":"QTRK-H","ST_CAT_NAME":"其他入库单-红字","ST_DOC_CLASS":"RKD","ST_APPROVAL_TYPE":null,"PROCESS_ID":null,"PC_W_FORM_ID":null,"PC_A_FORM_ID":null,"PC_P_FORM_ID":null,"M_W_FORM_ID":null,"M_A_FORM_ID":null,"ATT_CAT_CODE":null,"DESCRIPTION":null,"STATUS":null,"CREATION_DATE":null,"CREATED_BY":null,"LAST_UPDATE_DATE":null,"LAST_UPDATED_BY":null}
{"ST_CAT_CODE":"XSCK","ST_CAT_NAME":"销售出库单","ST_DOC_CLASS":"CKD","ST_APPROVAL_TYPE":null,"PROCESS_ID":null,"PC_W_FORM_ID":null,"PC_A_FORM_ID":null,"PC_P_FORM_ID":null,"M_W_FORM_ID":null,"M_A_FORM_ID":null,"ATT_CAT_CODE":null,"DESCRIPTION":null,"STATUS":null,"CREATION_DATE":null,"CREATED_BY":null,"LAST_UPDATE_DATE":null,"LAST_UPDATED_BY":null}
{"ST_CAT_CODE":"XSTK","ST_CAT_NAME":"销售退库单","ST_DOC_CLASS":"CKD","ST_APPROVAL_TYPE":null,"PROCESS_ID":null,"PC_W_FORM_ID":null,"PC_A_FORM_ID":null,"PC_P_FORM_ID":null,"M_W_FORM_ID":null,"M_A_FORM_ID":null,"ATT_CAT_CODE":null,"DESCRIPTION":null,"STATUS":null,"CREATION_DATE":null,"CREATED_BY":null,"LAST_UPDATE_DATE":null,"LAST_UPDATED_BY":null}